Metadata-Version: 2.1
Name: seqslab-cli
Version: 3.3.12
Summary: Atgenomix SeqsLab Command Line Tool
Home-page: https://github.com/AnomeGAP/seqslab-cli
Author: Allen Chang
Author-email: allen.chang@atgenomix.com
License: Apache License, Version 2.0
Project-URL: Documentation, https://docs.atgenomix.com/
Project-URL: Repository, https://github.com/atgenomix/seqslab-cli
Platform: UNKNOWN
Classifier: Intended Audience :: Developers
Classifier: License :: OSI Approved :: MIT License
Classifier: Operating System :: OS Independent
Classifier: Programming Language :: Python
Classifier: Programming Language :: Python :: 3.8
Classifier: Programming Language :: Python :: 3.9
Requires-Python: >=3.8
Requires-Dist: pip>=22.0.4
Requires-Dist: click==8.1.7
Requires-Dist: tabulate==0.9.0
Requires-Dist: terminaltables==3.1.10
Requires-Dist: cryptography==42.0.7
Requires-Dist: jeepney==0.8.0
Requires-Dist: secretstorage==3.3.3
Requires-Dist: dbus-python==1.2.16
Requires-Dist: keyring==24.3.0
Requires-Dist: numba==0.58.1
Requires-Dist: python-nubia==0.2b5
Requires-Dist: msal==1.26.0
Requires-Dist: tenacity==8.3.0
Requires-Dist: aiofiles==23.2.1
Requires-Dist: aiohttp[speedups]==3.9.5
Requires-Dist: aioretry==5.0.2
Requires-Dist: uvloop==0.19.0
Requires-Dist: arrow==1.3.0
Requires-Dist: yarl==1.4.2
Requires-Dist: requests-toolbelt==1.0.0
Requires-Dist: PyJWT==2.8.0
Requires-Dist: django-environ==0.11.2
Requires-Dist: validators==0.28.3
Requires-Dist: pydot==2.0.0
Requires-Dist: orjson==3.10.3
Requires-Dist: pydantic~=2.7.3
Requires-Dist: aiohttp-retry==2.8.3
Requires-Dist: requests~=2.32.3
Requires-Dist: setuptools~=70.0.0
Requires-Dist: jsonpath-ng==1.6.0
Requires-Dist: tzlocal==5.2
Requires-Dist: pytz==2021.3
